[
  {
    "id": "streetart",
    "title": {
      "en": "Street-art Hunters",
      "fr": "Street-art Hunters"
    },
    "image": "/src/assets/street-art-devices2.png",
    "description": {
      "en": "Street-Art Hunters is a project I developed with two classmates during my studies.",
      "fr": "Street-Art Hunters est un projet que j'ai développé avec deux de mes camarades pendant mes études."
    },
    "usage": {
      "en": "Use your camera to capture city street art, and accumulate points for each discovery!",
      "fr": "Utilisez votre téléphone pour capturer les street-arts à Bordeaux et accumulez des points pour chaque découverte !"
    },
    "technologies": [
      "React.js",
      "Node.js",
      "Express.js",
      "REST API",
      "Google Maps",
      "Live location"
    ],
    "functionalities": {
      "en": [
        "Secured authentication with tokens",
        "Passwords stored using bcrypt",
        "Relational database with MySQL",
        "MVC architecture",
        "Google Maps Integration",
        "Real-time Geolocation",
        "Photo functionality to take pictures"
      ],
      "fr": [
        "Authentification par tokens",
        "Stockage et hachage des mots de passe avec bcrypt",
        "Base de données relationnelle MySQL",
        "Architecture MVC",
        "Intégration de Google Maps",
        "Géolocalisation en temps réel",
        "Fonctionnalité de prise de photos"
      ]
    },
    "link": "https://street-art-hunter.laloupe-1.wilders.dev/map",
    "linkText": {
      "en": "Click here to play !",
      "fr": "Cliquez ici pour jouer !"
    }
  },
  {
    "id": "eshop",
    "title": {
      "en": "E-shop",
      "fr": "E-shop"
    },
    "image": "/src/assets/Eshop.png",
    "description": {
      "en": "Eshop is a project I am currently developing. It's a simple ecommerce website that allows you to browse through products and complete your purchase.",
      "fr": "Eshop est un projet que je développe actuellement. C'est une site de e-commerce qui se veut simple avec différentes fonctionnalités."
    },
    "usage": {
      "en": "Please browse through the articles and purchase some articles (stripe test mode only)!",
      "fr": "N'hésitez pas à parcourir les articles !"
    },
    "technologies": [
      "React.js",
      "Node.js",
      "Express.js",
      "REST API",
      "Stripe",
      "Sequelize"
    ],
    "functionalities": {
      "en": [
        "Stripe (test mode)",
        "Secured authentication with tokens",
        "Passwords stored using bcrypt",
        "Relational database with MySQL",
        "Microservices architecture"
      ],
      "fr": [
        "Stripe (mode test)",
        "Authentification sécurisée (tokens)",
        "Mots de passe stockés avec bcrypt",
        "Base de données relationnelle MySQL",
        "Architecture microservices"
      ]
    },
    "link": "https://github.com/LeslieCore34/Eshop",
    "linkText": {
      "en": "Checkout my code !",
      "fr": "Voir mon code ici !"
    }
  }
]
